covid_spike_classification/__init__.py
covid_spike_classification/__main__.py
covid_spike_classification/config.py
covid_spike_classification/core.py
covid_spike_classification-0.6.4.dist-info/LICENSE
covid_spike_classification-0.6.4.dist-info/METADATA
covid_spike_classification-0.6.4.dist-info/WHEEL
covid_spike_classification-0.6.4.dist-info/entry_points.txt
covid_spike_classification-0.6.4.dist-info/top_level.txt
covid_spike_classification-0.6.4.dist-info/RECORD
