Metadata-Version: 2.1
Name: covid-spike-classification
Version: 0.6.4
Summary: Detect interesting SARS-CoV-2 spike protein variants from Sanger sequencing data.
Home-page: https://github.com/kblin/covid-spike-classification/
Author: Kai Blin
Author-email: kblin@biosustain.dtu.dk
License: Apache Software License
Platform: UNKNOWN
Classifier: Programming Language :: Python
Classifier: Programming Language :: Python :: 3
Classifier: Development Status :: 3 - Alpha
Classifier: Intended Audience :: Science/Research
Classifier: Topic :: Scientific/Engineering :: Bio-Informatics
Classifier: License :: OSI Approved :: Apache Software License
Classifier: Operating System :: OS Independent
License-File: LICENSE
Requires-Dist: biopython
Provides-Extra: testing
Requires-Dist: flake8 ; extra == 'testing'
Requires-Dist: pytest ; extra == 'testing'
